lbom/__init__.py
lbom/main.py
lbom/bom/BomHandler.py
lbom/bom/BomHandlerCyclonedx.py
lbom/bom/__init__.py
lbom/clearly_defined/ClearlyDefinedClient.py
lbom/clearly_defined/ClearlyDefinedDetail.py
lbom/clearly_defined/ClearlyDefinedProviders.py
lbom/clearly_defined/__init__.py
lbom/license/LicenseResolver.py
lbom/license/__init__.py
lbom/utils/Utils.py
lbom/utils/__init__.py
lbom-0.6.dist-info/LICENSE
lbom-0.6.dist-info/METADATA
lbom-0.6.dist-info/WHEEL
lbom-0.6.dist-info/entry_points.txt
lbom-0.6.dist-info/top_level.txt
lbom-0.6.dist-info/RECORD
