Metadata-Version: 2.1
Name: lbom
Version: 0.6
Summary: A powerful tool filling licenses to CycloneDX files
Author: kaptain-ops
License: MIT License
Project-URL: Homepage, https://github.com/kaptain-ops/lbom
Keywords: CycloneDX,cdxgen,clearlydefined,license
Classifier: License :: OSI Approved :: MIT License
Classifier: Programming Language :: Python
Classifier: Programming Language :: Python :: 3
Requires-Python: >=3.9
License-File: LICENSE
Requires-Dist: requests >=2.31.0
Requires-Dist: packageurl-python >=0.14.0
